COPYING
README.md
setup.cfg
setup.py
geomesh/__init__.py
geomesh/__main__.py
geomesh/cmd.py
geomesh/crs.py
geomesh/db.py
geomesh/driver.py
geomesh/figures.py
geomesh/interp.py
geomesh/raster.py
geomesh/utils.py
geomesh.egg-info/PKG-INFO
geomesh.egg-info/SOURCES.txt
geomesh.egg-info/dependency_links.txt
geomesh.egg-info/entry_points.txt
geomesh.egg-info/requires.txt
geomesh.egg-info/top_level.txt
geomesh/cmd/__init__.py
geomesh/cmd/mesh_upgrader.py
geomesh/cmd/remesh.py
geomesh/geom/__init__.py
geomesh/geom/base.py
geomesh/geom/collector.py
geomesh/geom/geom.py
geomesh/geom/mesh.py
geomesh/geom/raster.py
geomesh/geom/shapely.py
geomesh/hfun/__init__.py
geomesh/hfun/base.py
geomesh/hfun/collector.py
geomesh/hfun/hfun.py
geomesh/hfun/mesh.py
geomesh/hfun/raster.py
geomesh/mesh/__init__.py
geomesh/mesh/base.py
geomesh/mesh/mesh.py
geomesh/mesh/parsers/__init__.py
geomesh/mesh/parsers/grd.py
geomesh/mesh/parsers/sms2dm.py
geomesh/ops/__init__.py
geomesh/ops/combine_geom.py
geomesh/ops/combine_hfun.py
tests/__init__.py
tests/test_meshrefine.py