Metadata-Version: 2.1
Name: geomesh
Version: 0.0.4
Summary: Package to generate computational unstructured meshes from planetary modeling.
Home-page: UNKNOWN
Author: Jaime R Calzada
Author-email: jreniel@gmail.com
License: GPL
Platform: UNKNOWN
Requires-Python: >=3.6, <=3.8
License-File: COPYING
